MANIFEST.in
README
setup.cfg
setup.py
extcmd/__init__.py
extcmd/test.py
extcmd.egg-info/PKG-INFO
extcmd.egg-info/SOURCES.txt
extcmd.egg-info/dependency_links.txt
extcmd.egg-info/top_level.txt
extcmd.egg-info/zip-safe